Metadata-Version: 2.1
Name: speck
Version: 0.1.8
Summary: Speck - Development and observability toolkit for LLM apps.
Home-page: https://github.com/speckai/speck-llm-observability
Download-URL: https://github.com/speckai/speck-llm-observability/archive/refs/tags/v0.1.8.tar.gz
Author: 
Author-email: Lucas Jaggernauth <luke@getspeck.ai>, Raghav Pillai <raghav@getspeck.ai>
Keywords: speck,openai,llm,ai,chat,bot,gpt,gpt-3,gpt-4,anthropic,replicate,litellm,observability
Classifier: Programming Language :: Python :: 3.12
Classifier: Programming Language :: Python :: 3.11
Classifier: Programming Language :: Python :: 3.10
Classifier: Programming Language :: Python :: 3.9
Classifier: Programming Language :: Python :: 3.8
Requires-Dist: openai
Requires-Dist: replicate
Requires-Dist: requests
Requires-Dist: pydantic
Requires-Dist: httpx
Requires-Dist: websockets
Requires-Dist: litellm
